Workbook

Sheet Premissas
A1: GTK PRÉ-MOLDADOS — PREMISSAS DO MODELO (edite apenas as células AZUIS; amarelas = premissas-chave)
A2: Fontes: proposta Gervasi REV00 12/05/2026; SINAPI-ES 06/2026; referências do Estudo de Mercado ago/2026 (ver fontes.md)
A4: Produção XP350 (por turno de 8h, fator 90% — proposta Gervasi)
A5: Bloco 14x19x39 — peças/turno | B5: 7020 | C5: Proposta Gervasi p.3
A6: Bloco 9x19x39 — peças/turno | B6: 10530 | C6: Proposta Gervasi p.3
A7: Bloco 19x19x39 — peças/turno | B7: 5265 | C7: Proposta Gervasi p.3
A8: Paver H6 — m²/turno | B8: 530 | C8: Proposta Gervasi p.3 (dígitos comprimidos; ver estudo §3.3)
A9: Dias úteis/mês | B9: 22 | C9: premissa
A10: Preços de venda posto fábrica (R$/un ou R$/m²)
A11: Bloco 14 vedação | B11: 3.3 | C11: Estudo §6.4 (10–25% abaixo da mediana SINAPI-ES)
A12: Bloco 14 estrutural fbk 6–8 | B12: 4.5 | C12: Estudo §6.4
A13: Bloco 9 vedação | B13: 2.8 | C13: Estudo §6.4
A14: Bloco 19 estrutural | B14: 5.5 | C14: Estudo §6.4
A15: Paver 35 MPa e=6 (m²) | B15: 57 | C15: Estudo §6.4
A16: Custos de insumos (posto fábrica)
A17: Cimento a granel (R$/kg) | B17: 0.55 | C17: R$ 450/t + frete — ref. nacional 2025 [fontes.md]
A18: Agregados mix (R$/m³) | B18: 165 | C18: SINAPI-ES 06/2026 + frete
A19: Consumo cimento bloco 14 vedação (kg/un) | B19: 1 | C19: WM Máquinas + traço típico; Gervasi economiza até 15%
A20: Consumo concreto bloco 14 (m³/un) | B20: 0.0054 | C20: 5,4 m³/h ÷ 1.000 pç/h (proposta)
A21: Aditivo+energia+diesel (R$/un bloco 14) | B21: 0.12 | C21: Estudo §13.2
A22: Mão de obra direta (R$/mês, 6 pessoas c/ encargos) | B22: 32000 | C22: CCT construção ES 2025/27 + encargos
A23: Manutenção e moldes (R$/un) | B23: 0.08 | C23: provisão
A24: Tributos s/ receita (Simples ind.) | B24: 0.085 | C24: faixa relevante — validar c/ contador
A25: Frete médio embutido s/ receita | B25: 0.045 | C25: parcela CIF do mix
A26: Custo fixo desembolsável (R$/mês) | B26: 52000 | C26: Estudo §13.3
A27: Margem de contribuição média do mix (% receita) | B27: 0.35 | C27: Estudo §13.4 — mix vedação+estrutural+paver
A28: Serviço da dívida FNE estimado (R$/mês, SAC pós-carência) | B28: 60000 | C28: ≈R$ 5 mi, 10 anos SAC — substituir pela simulação BNB

Sheet Capacidade
A1: CAPACIDADE DE PRODUÇÃO — LINHA GERVASI XP350
A3: Produto | B3: Peças/bandeja | C3: Peças/hora | D3: Por turno 8h (90%) | E3: Por mês (1 turno) | F3: Por ano (1 turno) | G3: Por ano (2 turnos) | H3: Concreto (m³/h)
A4: Bloco 14×19×39 (un) | B4: 4 | C4: 1000 | D4: =Premissas!$B$5 | E4: =D4*Premissas!$B$9 | F4: =E4*12 | G4: =F4*2 | H4: 5.4
A5: Bloco 9×19×39 (un) | B5: 6 | C5: 1200 | D5: =Premissas!$B$6 | E5: =D5*Premissas!$B$9 | F5: =E5*12 | G5: =F5*2 | H5: 7.3
A6: Bloco 19×19×39 (un) | B6: 3 | C6: 750 | D6: =Premissas!$B$7 | E6: =D6*Premissas!$B$9 | F6: =E6*12 | G6: =F6*2 | H6: 4.7
A7: Paver H6 (m²) | B7: 0.37 | C7: 74 | D7: =Premissas!$B$8 | E7: =D7*Premissas!$B$9 | F7: =E7*12 | G7: =F7*2 | H7: 4.1
A9: Nota: valores por turno conforme proposta Gervasi (fator 90%). Troca de molde: 15–20 min. Silo 90 t ≈ 13 dias úteis de autonomia em produção plena de bloco 14.

Sheet Custo Unitário
A1: CUSTO VARIÁVEL E MARGEM POR PRODUTO (bloco 14 vedação detalhado; demais derivados)
A3: Bloco 14×19×39 — vedação
A4: Cimento (kg × R$/kg) | B4: =Premissas!$B$19*Premissas!$B$17
A5: Agregados (m³ × R$/m³) | B5: =Premissas!$B$20*Premissas!$B$18
A6: Aditivo + energia + diesel | B6: =Premissas!$B$21
A7: Mão de obra direta (rateio mensal ÷ produção) | B7: =Premissas!$B$22/(Premissas!$B$5*Premissas!$B$9)
A8: Manutenção e moldes | B8: =Premissas!$B$23
A9: CUSTO VARIÁVEL INDUSTRIAL (un) | B9: =SUM(B4:B8)
A10: Tributos sobre venda (% × PV) | B10: =Premissas!$B$24*Premissas!$B$11
A11: Frete embutido (% × PV) | B11: =Premissas!$B$25*Premissas!$B$11
A12: CUSTO VARIÁVEL TOTAL (un) | B12: =B9+B10+B11
A13: Preço de venda — bloco 14 vedação | B13: =Premissas!$B$11
A14: MARGEM DE CONTRIBUIÇÃO (R$/un) | B14: =B13-B12
A15: MARGEM DE CONTRIBUIÇÃO (%) | B15: =B14/B13
A17: Margens indicativas dos demais produtos (traço mais rico no estrutural/paver — estudo §13.2)
A18: Produto | B18: PV (R$) | C18: CV total (R$) | D18: MC (R$) | E18: MC (%)
A19: Bloco 9 vedação | B19: =Premissas!$B$13 | C19: 2.05 | D19: =B19-C19 | E19: =D19/B19
A20: Bloco 14 estrutural fbk 6–8 | B20: =Premissas!$B$12 | C20: 2.6 | D20: =B20-C20 | E20: =D20/B20
A21: Bloco 19 estrutural | B21: =Premissas!$B$14 | C21: 3.3 | D21: =B21-C21 | E21: =D21/B21
A22: Paver e=6 (m²) | B22: =Premissas!$B$15 | C22: 30 | D22: =B22-C22 | E22: =D22/B22

Sheet Cenários
A1: CENÁRIOS DE UTILIZAÇÃO (1 turno) — RECEITA, EBITDA E PONTO DE EQUILÍBRIO
A3: Receita anual a 100% de 1 turno (mix do estudo §5.4/§13): | B3: 7000000 | C3: mix: 60% bloco14 (ved+estr), 15% bloco 9, 10% bloco 19/canaleta, 15% paver
A5: Cenário | B5: Utilização | C5: Receita anual | D5: Margem contribuição | E5: Custos fixos ano | F5: EBITDA | G5: EBITDA – dívida FNE
A6: Pessimista (ano 1 fraco) | B6: 0.35 | C6: =$B$3*B6 | D6: =C6*Premissas!$B$27 | E6: =Premissas!$B$26*12 | F6: =D6-E6 | G6: =F6-Premissas!$B$28*12
A7: Base ano 1 | B7: 0.425 | C7: =$B$3*B7 | D7: =C7*Premissas!$B$27 | E7: =Premissas!$B$26*12 | F7: =D7-E7 | G7: =F7-Premissas!$B$28*12
A8: Base ano 2 | B8: 0.6 | C8: =$B$3*B8 | D8: =C8*Premissas!$B$27 | E8: =Premissas!$B$26*12 | F8: =D8-E8 | G8: =F8-Premissas!$B$28*12
A9: Base ano 3 (regime) | B9: 0.775 | C9: =$B$3*B9 | D9: =C9*Premissas!$B$27 | E9: =Premissas!$B$26*12 | F9: =D9-E9 | G9: =F9-Premissas!$B$28*12
A10: Pleno 1 turno | B10: 0.95 | C10: =$B$3*B10 | D10: =C10*Premissas!$B$27 | E10: =Premissas!$B$26*12 | F10: =D10-E10 | G10: =F10-Premissas!$B$28*12
A13: Ponto de equilíbrio
A14: Receita de equilíbrio operacional (R$/mês) | B14: =Premissas!$B$26/Premissas!$B$27
A15: Equilíbrio operacional (% da capacidade de 1 turno) | B15: =B14*12/$B$3
A16: Receita de equilíbrio com dívida FNE (R$/mês) | B16: =(Premissas!$B$26+Premissas!$B$28)/Premissas!$B$27
A17: Equilíbrio com dívida (% da capacidade de 1 turno) | B17: =B16*12/$B$3

Sheet CAPEX e Funding
A1: INVESTIMENTO TOTAL DO PROJETO (valores médios das faixas do estudo §13.1)
A3: Item | B3: Valor (R$) | C3: Observação
A4: Linha Gervasi XP350 completa (proposta REV00 12/05/2026) | B4: 2723000 | C4: contratada; R$ 600 mil pagos
A5: Galpão industrial ≈1.500 m² + piso + fundações | B5: 2250000 | C5: R$ 1.250–1.900/m² (média adotada 1.500)
A6: Terraplanagem, pátio, acessos, cerca, água | B6: 450000 | C6: faixa 350–550 mil
A7: Entrada de energia MT + instalações elétricas | B7: 150000 | C7: subestação simplificada EDP ≤300 kVA
A8: Bandejas (≈5.000) + gaiolas de cura + pallets | B8: 350000 | C8: faixa 280–420 mil — item não incluso na proposta
A9: Pá carregadeira + empilhadeira (seminovas) | B9: 350000 | C9: faixa 280–420 mil
A10: Compressor, ferramentas, laboratório interno, EPIs | B10: 75000 | C10: faixa 60–90 mil
A11: Licenças, projetos, ART, consultorias, seguros | B11: 80000 | C11: faixa 60–100 mil
A12: Montagem, frete FOB Içara-SC, startup | B12: 150000 | C12: faixa 120–180 mil
A13: SUBTOTAL CAPEX | B13: =SUM(B4:B12)
A14: Capital de giro inicial | B14: 800000 | C14: faixa 700–900 mil — ciclo financeiro 45–60 dias
A15: INVESTIMENTO TOTAL | B15: =B13+B14
A17: Funding indicativo
A18: FNE/BNB (equipamentos + obras civis financiáveis) | B18: =0.65*B15 | C18: ≈65% — calibrar no projeto de crédito
A19: Recursos próprios (capital social subscrito R$ 7,5 mi) | B19: =B15-B18
